[
   {
      "category": "Best Actor in a Leading Role",
      "nominations": [
         {
            "notes": null,
            "won": true,
            "primary": [
               {
                  "name": "William Hurt",
                  "notes": null,
                  "imdb_id": "nm0000458"
               }
            ],
            "secondary": [
               {
                  "name": "Kiss of the Spider Woman",
                  "notes": null,
                  "imdb_id": "tt0089424"
               }
            ]
         },
         {
            "notes": null,
            "won": false,
            "primary": [
               {
                  "name": "Harrison Ford",
                  "notes": null,
                  "imdb_id": "nm0000148"
               }
            ],
            "secondary": [
               {
                  "name": "Witness",
                  "notes": null,
                  "imdb_id": "tt0090329"
               }
            ]
         },
         {
            "notes": null,
            "won": false,
            "primary": [
               {
                  "name": "Jack Nicholson",
                  "notes": null,
                  "imdb_id": "nm0000197"
               }
            ],
            "secondary": [
               {
                  "name": "Prizzi's Honor",
                  "notes": null,
                  "imdb_id": "tt0089841"
               }
            ]
         },
         {
            "notes": null,
            "won": false,
            "primary": [
               {
                  "name": "James Garner",
                  "notes": null,
                  "imdb_id": "nm0001258"
               }
            ],
            "secondary": [
               {
                  "name": "Murphy's Romance",
                  "notes": null,
                  "imdb_id": "tt0089643"
               }
            ]
         },
         {
            "notes": null,
            "won": false,
            "primary": [
               {
                  "name": "Jon Voight",
                  "notes": null,
                  "imdb_id": "nm0000685"
               }
            ],
            "secondary": [
               {
                  "name": "Runaway Train",
                  "notes": null,
                  "imdb_id": "tt0089941"
               }
            ]
         }
      ]
   },
   {
      "category": "Best Actor in a Supporting Role",
      "nominations": [
         {
            "notes": null,
            "won": true,
            "primary": [
               {
                  "name": "Don Ameche",
                  "notes": null,
                  "imdb_id": "nm0000747"
               }
            ],
            "secondary": [
               {
                  "name": "Cocoon",
                  "notes": null,
                  "imdb_id": "tt0088933"
               }
            ]
         },
         {
            "notes": null,
            "won": false,
            "primary": [
               {
                  "name": "Eric Roberts",
                  "notes": null,
                  "imdb_id": "nm0000616"
               }
            ],
            "secondary": [
               {
                  "name": "Runaway Train",
                  "notes": null,
                  "imdb_id": "tt0089941"
               }
            ]
         },
         {
            "notes": null,
            "won": false,
            "primary": [
               {
                  "name": "Klaus Maria Brandauer",
                  "notes": null,
                  "imdb_id": "nm0001970"
               }
            ],
            "secondary": [
               {
                  "name": "Out of Africa",
                  "notes": null,
                  "imdb_id": "tt0089755"
               }
            ]
         },
         {
            "notes": null,
            "won": false,
            "primary": [
               {
                  "name": "Robert Loggia",
                  "notes": null,
                  "imdb_id": "nm0005162"
               }
            ],
            "secondary": [
               {
                  "name": "Jagged Edge",
                  "notes": null,
                  "imdb_id": "tt0089360"
               }
            ]
         },
         {
            "notes": null,
            "won": false,
            "primary": [
               {
                  "name": "William Hickey",
                  "notes": null,
                  "imdb_id": "nm0382676"
               }
            ],
            "secondary": [
               {
                  "name": "Prizzi's Honor",
                  "notes": null,
                  "imdb_id": "tt0089841"
               }
            ]
         }
      ]
   },
   {
      "category": "Best Actress in a Leading Role",
      "nominations": [
         {
            "notes": null,
            "won": true,
            "primary": [
               {
                  "name": "Geraldine Page",
                  "notes": null,
                  "imdb_id": "nm0656183"
               }
            ],
            "secondary": [
               {
                  "name": "The Trip to Bountiful",
                  "notes": null,
                  "imdb_id": "tt0090203"
               }
            ]
         },
         {
            "notes": null,
            "won": false,
            "primary": [
               {
                  "name": "Anne Bancroft",
                  "notes": null,
                  "imdb_id": "nm0000843"
               }
            ],
            "secondary": [
               {
                  "name": "Agnes of God",
                  "notes": null,
                  "imdb_id": "tt0088683"
               }
            ]
         },
         {
            "notes": null,
            "won": false,
            "primary": [
               {
                  "name": "Jessica Lange",
                  "notes": null,
                  "imdb_id": "nm0001448"
               }
            ],
            "secondary": [
               {
                  "name": "Sweet Dreams",
                  "notes": null,
                  "imdb_id": "tt0090110"
               }
            ]
         },
         {
            "notes": null,
            "won": false,
            "primary": [
               {
                  "name": "Meryl Streep",
                  "notes": null,
                  "imdb_id": "nm0000658"
               }
            ],
            "secondary": [
               {
                  "name": "Out of Africa",
                  "notes": null,
                  "imdb_id": "tt0089755"
               }
            ]
         },
         {
            "notes": null,
            "won": false,
            "primary": [
               {
                  "name": "Whoopi Goldberg",
                  "notes": null,
                  "imdb_id": "nm0000155"
               }
            ],
            "secondary": [
               {
                  "name": "The Color Purple",
                  "notes": null,
                  "imdb_id": "tt0088939"
               }
            ]
         }
      ]
   },
   {
      "category": "Best Actress in a Supporting Role",
      "nominations": [
         {
            "notes": null,
            "won": true,
            "primary": [
               {
                  "name": "Anjelica Huston",
                  "notes": null,
                  "imdb_id": "nm0001378"
               }
            ],
            "secondary": [
               {
                  "name": "Prizzi's Honor",
                  "notes": null,
                  "imdb_id": "tt0089841"
               }
            ]
         },
         {
            "notes": null,
            "won": false,
            "primary": [
               {
                  "name": "Amy Madigan",
                  "notes": null,
                  "imdb_id": "nm0001496"
               }
            ],
            "secondary": [
               {
                  "name": "Twice in a Lifetime",
                  "notes": null,
                  "imdb_id": "tt0090223"
               }
            ]
         },
         {
            "notes": null,
            "won": false,
            "primary": [
               {
                  "name": "Margaret Avery",
                  "notes": null,
                  "imdb_id": "nm0001923"
               }
            ],
            "secondary": [
               {
                  "name": "The Color Purple",
                  "notes": null,
                  "imdb_id": "tt0088939"
               }
            ]
         },
         {
            "notes": null,
            "won": false,
            "primary": [
               {
                  "name": "Meg Tilly",
                  "notes": null,
                  "imdb_id": "nm0000672"
               }
            ],
            "secondary": [
               {
                  "name": "Agnes of God",
                  "notes": null,
                  "imdb_id": "tt0088683"
               }
            ]
         },
         {
            "notes": null,
            "won": false,
            "primary": [
               {
                  "name": "Oprah Winfrey",
                  "notes": null,
                  "imdb_id": "nm0001856"
               }
            ],
            "secondary": [
               {
                  "name": "The Color Purple",
                  "notes": null,
                  "imdb_id": "tt0088939"
               }
            ]
         }
      ]
   },
   {
      "category": "Best Art Direction-Set Decoration",
      "nominations": [
         {
            "notes": null,
            "won": true,
            "primary": [
               {
                  "name": "Out of Africa",
                  "notes": null,
                  "imdb_id": "tt0089755"
               }
            ],
            "secondary": [
               {
                  "name": "Stephen B. Grimes",
                  "notes": null,
                  "imdb_id": "nm0342242"
               },
               {
                  "name": "Josie MacAvin",
                  "notes": null,
                  "imdb_id": "nm0531357"
               }
            ]
         },
         {
            "notes": null,
            "won": false,
            "primary": [
               {
                  "name": "Brazil",
                  "notes": null,
                  "imdb_id": "tt0088846"
               }
            ],
            "secondary": [
               {
                  "name": "Norman Garwood",
                  "notes": null,
                  "imdb_id": "nm0308841"
               },
               {
                  "name": "Maggie Gray",
                  "notes": null,
                  "imdb_id": "nm0336799"
               }
            ]
         },
         {
            "notes": null,
            "won": false,
            "primary": [
               {
                  "name": "Ran",
                  "notes": null,
                  "imdb_id": "tt0089881"
               }
            ],
            "secondary": [
               {
                  "name": "Yoshir\u00f4 Muraki",
                  "notes": null,
                  "imdb_id": "nm0613499"
               },
               {
                  "name": "Shinobu Muraki",
                  "notes": null,
                  "imdb_id": "nm0613502"
               }
            ]
         },
         {
            "notes": null,
            "won": false,
            "primary": [
               {
                  "name": "The Color Purple",
                  "notes": null,
                  "imdb_id": "tt0088939"
               }
            ],
            "secondary": [
               {
                  "name": "J. Michael Riva",
                  "notes": null,
                  "imdb_id": "nm0728951"
               },
               {
                  "name": "Bo Welch",
                  "notes": null,
                  "imdb_id": "nm0919514"
               },
               {
                  "name": "Linda DeScenna",
                  "notes": null,
                  "imdb_id": "nm0220984"
               }
            ]
         },
         {
            "notes": null,
            "won": false,
            "primary": [
               {
                  "name": "Witness",
                  "notes": null,
                  "imdb_id": "tt0090329"
               }
            ],
            "secondary": [
               {
                  "name": "Stan Jolley",
                  "notes": null,
                  "imdb_id": "nm0427164"
               },
               {
                  "name": "John H. Anderson",
                  "notes": null,
                  "imdb_id": "nm0026936"
               }
            ]
         }
      ]
   },
   {
      "category": "Best Cinematography",
      "nominations": [
         {
            "notes": null,
            "won": true,
            "primary": [
               {
                  "name": "Out of Africa",
                  "notes": null,
                  "imdb_id": "tt0089755"
               }
            ],
            "secondary": [
               {
                  "name": "David Watkin",
                  "notes": null,
                  "imdb_id": "nm0914239"
               }
            ]
         },
         {
            "notes": null,
            "won": false,
            "primary": [
               {
                  "name": "Murphy's Romance",
                  "notes": null,
                  "imdb_id": "tt0089643"
               }
            ],
            "secondary": [
               {
                  "name": "William A. Fraker",
                  "notes": null,
                  "imdb_id": "nm0005710"
               }
            ]
         },
         {
            "notes": null,
            "won": false,
            "primary": [
               {
                  "name": "Ran",
                  "notes": null,
                  "imdb_id": "tt0089881"
               }
            ],
            "secondary": [
               {
                  "name": "Takao Sait\u00f4",
                  "notes": null,
                  "imdb_id": "nm0756912"
               },
               {
                  "name": "Sh\u00f4ji Ueda",
                  "notes": null,
                  "imdb_id": "nm0879921"
               },
               {
                  "name": "Asakazu Nakai",
                  "notes": null,
                  "imdb_id": "nm0620014"
               }
            ]
         },
         {
            "notes": null,
            "won": false,
            "primary": [
               {
                  "name": "The Color Purple",
                  "notes": null,
                  "imdb_id": "tt0088939"
               }
            ],
            "secondary": [
               {
                  "name": "Allen Daviau",
                  "notes": null,
                  "imdb_id": "nm0005679"
               }
            ]
         },
         {
            "notes": null,
            "won": false,
            "primary": [
               {
                  "name": "Witness",
                  "notes": null,
                  "imdb_id": "tt0090329"
               }
            ],
            "secondary": [
               {
                  "name": "John Seale",
                  "notes": null,
                  "imdb_id": "nm0005868"
               }
            ]
         }
      ]
   },
   {
      "category": "Best Costume Design",
      "nominations": [
         {
            "notes": null,
            "won": true,
            "primary": [
               {
                  "name": "Ran",
                  "notes": null,
                  "imdb_id": "tt0089881"
               }
            ],
            "secondary": [
               {
                  "name": "Emi Wada",
                  "notes": null,
                  "imdb_id": "nm0905253"
               }
            ]
         },
         {
            "notes": null,
            "won": false,
            "primary": [
               {
                  "name": "Out of Africa",
                  "notes": null,
                  "imdb_id": "tt0089755"
               }
            ],
            "secondary": [
               {
                  "name": "Milena Canonero",
                  "notes": null,
                  "imdb_id": "nm0134382"
               }
            ]
         },
         {
            "notes": null,
            "won": false,
            "primary": [
               {
                  "name": "Prizzi's Honor",
                  "notes": null,
                  "imdb_id": "tt0089841"
               }
            ],
            "secondary": [
               {
                  "name": "Donfeld",
                  "notes": null,
                  "imdb_id": "nm0232466"
               }
            ]
         },
         {
            "notes": null,
            "won": false,
            "primary": [
               {
                  "name": "The Color Purple",
                  "notes": null,
                  "imdb_id": "tt0088939"
               }
            ],
            "secondary": [
               {
                  "name": "Aggie Guerard Rodgers",
                  "notes": null,
                  "imdb_id": "nm0345888"
               }
            ]
         },
         {
            "notes": null,
            "won": false,
            "primary": [
               {
                  "name": "The Journey of Natty Gann",
                  "notes": null,
                  "imdb_id": "tt0089385"
               }
            ],
            "secondary": [
               {
                  "name": "Albert Wolsky",
                  "notes": null,
                  "imdb_id": "nm0938717"
               }
            ]
         }
      ]
   },
   {
      "category": "Best Director",
      "nominations": [
         {
            "notes": null,
            "won": true,
            "primary": [
               {
                  "name": "Sydney Pollack",
                  "notes": null,
                  "imdb_id": "nm0001628"
               }
            ],
            "secondary": [
               {
                  "name": "Out of Africa",
                  "notes": null,
                  "imdb_id": "tt0089755"
               }
            ]
         },
         {
            "notes": null,
            "won": false,
            "primary": [
               {
                  "name": "Akira Kurosawa",
                  "notes": null,
                  "imdb_id": "nm0000041"
               }
            ],
            "secondary": [
               {
                  "name": "Ran",
                  "notes": null,
                  "imdb_id": "tt0089881"
               }
            ]
         },
         {
            "notes": null,
            "won": false,
            "primary": [
               {
                  "name": "Hector Babenco",
                  "notes": null,
                  "imdb_id": "nm0002199"
               }
            ],
            "secondary": [
               {
                  "name": "Kiss of the Spider Woman",
                  "notes": null,
                  "imdb_id": "tt0089424"
               }
            ]
         },
         {
            "notes": null,
            "won": false,
            "primary": [
               {
                  "name": "John Huston",
                  "notes": null,
                  "imdb_id": "nm0001379"
               }
            ],
            "secondary": [
               {
                  "name": "Prizzi's Honor",
                  "notes": null,
                  "imdb_id": "tt0089841"
               }
            ]
         },
         {
            "notes": null,
            "won": false,
            "primary": [
               {
                  "name": "Peter Weir",
                  "notes": null,
                  "imdb_id": "nm0001837"
               }
            ],
            "secondary": [
               {
                  "name": "Witness",
                  "notes": null,
                  "imdb_id": "tt0090329"
               }
            ]
         }
      ]
   },
   {
      "category": "Best Documentary, Features",
      "nominations": [
         {
            "notes": null,
            "won": true,
            "primary": [
               {
                  "name": "Broken Rainbow",
                  "notes": null,
                  "imdb_id": "tt0088857"
               }
            ],
            "secondary": [
               {
                  "name": "Maria Florio",
                  "notes": null,
                  "imdb_id": "nm0283061"
               },
               {
                  "name": "Victoria Mudd",
                  "notes": null,
                  "imdb_id": "nm0610927"
               }
            ]
         },
         {
            "notes": null,
            "won": false,
            "primary": [
               {
                  "name": "Soldiers in Hiding",
                  "notes": null,
                  "imdb_id": "tt0090043"
               }
            ],
            "secondary": [
               {
                  "name": "Japhet Asher",
                  "notes": null,
                  "imdb_id": "nm0038871"
               }
            ]
         },
         {
            "notes": null,
            "won": false,
            "primary": [
               {
                  "name": "The Mothers of the Plaza of Mayo",
                  "notes": null,
                  "imdb_id": "tt0089460"
               }
            ],
            "secondary": [
               {
                  "name": "Susana Blaustein Mu\u00f1oz",
                  "notes": null,
                  "imdb_id": "nm0087903"
               },
               {
                  "name": "Lourdes Portillo",
                  "notes": null,
                  "imdb_id": "nm0692409"
               }
            ]
         },
         {
            "notes": null,
            "won": false,
            "primary": [
               {
                  "name": "The Statue of Liberty",
                  "notes": null,
                  "imdb_id": "tt0092011"
               }
            ],
            "secondary": [
               {
                  "name": "Ken Burns",
                  "notes": null,
                  "imdb_id": "nm0122741"
               },
               {
                  "name": "Buddy Squires",
                  "notes": null,
                  "imdb_id": "nm0820113"
               }
            ]
         },
         {
            "notes": null,
            "won": false,
            "primary": [
               {
                  "name": "Unfinished Business",
                  "notes": null,
                  "imdb_id": "tt0092136"
               }
            ],
            "secondary": [
               {
                  "name": "Steven Okazaki",
                  "notes": null,
                  "imdb_id": "nm0645574"
               }
            ]
         }
      ]
   },
   {
      "category": "Best Documentary, Short Subjects",
      "nominations": [
         {
            "notes": null,
            "won": true,
            "primary": [
               {
                  "name": "Witness to War: Dr. Charlie Clements",
                  "notes": null,
                  "imdb_id": "tt0090330"
               }
            ],
            "secondary": [
               {
                  "name": "David Goodman",
                  "notes": null,
                  "imdb_id": "nm0329045"
               }
            ]
         },
         {
            "notes": null,
            "won": false,
            "primary": [
               {
                  "name": "Keats and His Nightingale: A Blind Date",
                  "notes": null,
                  "imdb_id": "tt0089408"
               }
            ],
            "secondary": [
               {
                  "name": "Michael Crowley",
                  "notes": null,
                  "imdb_id": "nm0189764"
               },
               {
                  "name": "Jim Wolpaw",
                  "notes": "(as James Wolpaw)",
                  "imdb_id": "nm0938673"
               }
            ]
         },
         {
            "notes": null,
            "won": false,
            "primary": [
               {
                  "name": "Making Overtures: The Story of a Community Orchestra",
                  "notes": null,
                  "imdb_id": "tt0089535"
               }
            ],
            "secondary": [
               {
                  "name": "Barbara Willis Sweete",
                  "notes": null,
                  "imdb_id": "nm0842318"
               }
            ]
         },
         {
            "notes": null,
            "won": false,
            "primary": [
               {
                  "name": "The Courage to Care",
                  "notes": null,
                  "imdb_id": "tt0088957"
               }
            ],
            "secondary": [
               {
                  "name": "Robert H. Gardner",
                  "notes": null,
                  "imdb_id": "nm0307089"
               }
            ]
         },
         {
            "notes": null,
            "won": false,
            "primary": [
               {
                  "name": "The Wizard of the Strings",
                  "notes": null,
                  "imdb_id": "tt0090332"
               }
            ],
            "secondary": [
               {
                  "name": "Alan Edelstein",
                  "notes": null,
                  "imdb_id": "nm0249037"
               }
            ]
         }
      ]
   },
   {
      "category": "Best Effects, Sound Effects Editing",
      "nominations": [
         {
            "notes": null,
            "won": true,
            "primary": [
               {
                  "name": "Back to the Future",
                  "notes": null,
                  "imdb_id": "tt0088763"
               }
            ],
            "secondary": [
               {
                  "name": "Charles L. Campbell",
                  "notes": null,
                  "imdb_id": "nm0132287"
               },
               {
                  "name": "Robert R. Rutledge",
                  "notes": null,
                  "imdb_id": "nm0752091"
               }
            ]
         },
         {
            "notes": null,
            "won": false,
            "primary": [
               {
                  "name": "Ladyhawke",
                  "notes": null,
                  "imdb_id": "tt0089457"
               }
            ],
            "secondary": [
               {
                  "name": "Robert G. Henderson",
                  "notes": null,
                  "imdb_id": "nm0376583"
               },
               {
                  "name": "Alan Robert Murray",
                  "notes": null,
                  "imdb_id": "nm0614812"
               }
            ]
         },
         {
            "notes": null,
            "won": false,
            "primary": [
               {
                  "name": "Rambo: First Blood Part II",
                  "notes": null,
                  "imdb_id": "tt0089880"
               }
            ],
            "secondary": [
               {
                  "name": "Fred J. Brown",
                  "notes": null,
                  "imdb_id": "nm0113578"
               }
            ]
         }
      ]
   },
   {
      "category": "Best Effects, Visual Effects",
      "nominations": [
         {
            "notes": null,
            "won": true,
            "primary": [
               {
                  "name": "Cocoon",
                  "notes": null,
                  "imdb_id": "tt0088933"
               }
            ],
            "secondary": [
               {
                  "name": "Ken Ralston",
                  "notes": null,
                  "imdb_id": "nm0707822"
               },
               {
                  "name": "Ralph McQuarrie",
                  "notes": null,
                  "imdb_id": "nm0574319"
               },
               {
                  "name": "Scott Farrar",
                  "notes": null,
                  "imdb_id": "nm0268141"
               },
               {
                  "name": "David Berry",
                  "notes": null,
                  "imdb_id": "nm0077529"
               }
            ]
         },
         {
            "notes": null,
            "won": false,
            "primary": [
               {
                  "name": "Return to Oz",
                  "notes": null,
                  "imdb_id": "tt0089908"
               }
            ],
            "secondary": [
               {
                  "name": "Will Vinton",
                  "notes": null,
                  "imdb_id": "nm0899139"
               },
               {
                  "name": "Ian Wingrove",
                  "notes": null,
                  "imdb_id": "nm0935071"
               },
               {
                  "name": "Zoran Perisic",
                  "notes": null,
                  "imdb_id": "nm0673830"
               },
               {
                  "name": "Michael Lloyd",
                  "notes": null,
                  "imdb_id": "nm0516084"
               }
            ]
         },
         {
            "notes": null,
            "won": false,
            "primary": [
               {
                  "name": "Young Sherlock Holmes",
                  "notes": null,
                  "imdb_id": "tt0090357"
               }
            ],
            "secondary": [
               {
                  "name": "Dennis Muren",
                  "notes": null,
                  "imdb_id": "nm0613830"
               },
               {
                  "name": "Kit West",
                  "notes": null,
                  "imdb_id": "nm0922187"
               },
               {
                  "name": "John Ellis",
                  "notes": null,
                  "imdb_id": "nm1290751"
               },
               {
                  "name": "David Allen",
                  "notes": null,
                  "imdb_id": "nm0020406"
               }
            ]
         }
      ]
   },
   {
      "category": "Best Film Editing",
      "nominations": [
         {
            "notes": null,
            "won": true,
            "primary": [
               {
                  "name": "Witness",
                  "notes": null,
                  "imdb_id": "tt0090329"
               }
            ],
            "secondary": [
               {
                  "name": "Thom Noble",
                  "notes": null,
                  "imdb_id": "nm0633677"
               }
            ]
         },
         {
            "notes": null,
            "won": false,
            "primary": [
               {
                  "name": "A Chorus Line",
                  "notes": null,
                  "imdb_id": "tt0088915"
               }
            ],
            "secondary": [
               {
                  "name": "John Bloom",
                  "notes": null,
                  "imdb_id": "nm0089182"
               }
            ]
         },
         {
            "notes": null,
            "won": false,
            "primary": [
               {
                  "name": "Out of Africa",
                  "notes": null,
                  "imdb_id": "tt0089755"
               }
            ],
            "secondary": [
               {
                  "name": "Fredric Steinkamp",
                  "notes": null,
                  "imdb_id": "nm0826114"
               },
               {
                  "name": "William Steinkamp",
                  "notes": null,
                  "imdb_id": "nm0826119"
               },
               {
                  "name": "Pembroke J. Herring",
                  "notes": null,
                  "imdb_id": "nm0380670"
               },
               {
                  "name": "Sheldon Kahn",
                  "notes": null,
                  "imdb_id": "nm0434922"
               }
            ]
         },
         {
            "notes": null,
            "won": false,
            "primary": [
               {
                  "name": "Prizzi's Honor",
                  "notes": null,
                  "imdb_id": "tt0089841"
               }
            ],
            "secondary": [
               {
                  "name": "Rudi Fehr",
                  "notes": null,
                  "imdb_id": "nm0270458"
               },
               {
                  "name": "Kaja Fehr",
                  "notes": null,
                  "imdb_id": "nm0270454"
               }
            ]
         },
         {
            "notes": null,
            "won": false,
            "primary": [
               {
                  "name": "Runaway Train",
                  "notes": null,
                  "imdb_id": "tt0089941"
               }
            ],
            "secondary": [
               {
                  "name": "Henry Richardson",
                  "notes": null,
                  "imdb_id": "nm0724572"
               }
            ]
         }
      ]
   },
   {
      "category": "Best Foreign Language Film",
      "nominations": [
         {
            "notes": "Argentina",
            "won": true,
            "primary": [
               {
                  "name": "The Official Story",
                  "notes": null,
                  "imdb_id": "tt0089276"
               }
            ],
            "secondary": []
         },
         {
            "notes": "West Germany",
            "won": false,
            "primary": [
               {
                  "name": "Angry Harvest",
                  "notes": null,
                  "imdb_id": "tt0088811"
               }
            ],
            "secondary": []
         },
         {
            "notes": "Hungary",
            "won": false,
            "primary": [
               {
                  "name": "Colonel Redl",
                  "notes": null,
                  "imdb_id": "tt0089716"
               }
            ],
            "secondary": []
         },
         {
            "notes": "France",
            "won": false,
            "primary": [
               {
                  "name": "Three Men and a Cradle",
                  "notes": null,
                  "imdb_id": "tt0090206"
               }
            ],
            "secondary": []
         },
         {
            "notes": "Yugoslavia",
            "won": false,
            "primary": [
               {
                  "name": "When Father Was Away on Business",
                  "notes": null,
                  "imdb_id": "tt0089748"
               }
            ],
            "secondary": []
         }
      ]
   },
   {
      "category": "Best Makeup",
      "nominations": [
         {
            "notes": null,
            "won": true,
            "primary": [
               {
                  "name": "Mask",
                  "notes": null,
                  "imdb_id": "tt0089560"
               }
            ],
            "secondary": [
               {
                  "name": "Michael Westmore",
                  "notes": null,
                  "imdb_id": "nm0922878"
               },
               {
                  "name": "Zoltan Elek",
                  "notes": null,
                  "imdb_id": "nm0253227"
               }
            ]
         },
         {
            "notes": null,
            "won": false,
            "primary": [
               {
                  "name": "Remo Williams: The Adventure Begins",
                  "notes": null,
                  "imdb_id": "tt0089901"
               }
            ],
            "secondary": [
               {
                  "name": "Carl Fullerton",
                  "notes": null,
                  "imdb_id": "nm0298379"
               }
            ]
         },
         {
            "notes": null,
            "won": false,
            "primary": [
               {
                  "name": "The Color Purple",
                  "notes": null,
                  "imdb_id": "tt0088939"
               }
            ],
            "secondary": [
               {
                  "name": "Ken Chase",
                  "notes": null,
                  "imdb_id": "nm0153793"
               }
            ]
         }
      ]
   },
   {
      "category": "Best Music, Original Score",
      "nominations": [
         {
            "notes": null,
            "won": true,
            "primary": [
               {
                  "name": "Out of Africa",
                  "notes": null,
                  "imdb_id": "tt0089755"
               }
            ],
            "secondary": [
               {
                  "name": "John Barry",
                  "notes": null,
                  "imdb_id": "nm0000290"
               }
            ]
         },
         {
            "notes": null,
            "won": false,
            "primary": [
               {
                  "name": "Agnes of God",
                  "notes": null,
                  "imdb_id": "tt0088683"
               }
            ],
            "secondary": [
               {
                  "name": "Georges Delerue",
                  "notes": null,
                  "imdb_id": "nm0000016"
               }
            ]
         },
         {
            "notes": null,
            "won": false,
            "primary": [
               {
                  "name": "Silverado",
                  "notes": null,
                  "imdb_id": "tt0090022"
               }
            ],
            "secondary": [
               {
                  "name": "Bruce Broughton",
                  "notes": null,
                  "imdb_id": "nm0005976"
               }
            ]
         },
         {
            "notes": null,
            "won": false,
            "primary": [
               {
                  "name": "The Color Purple",
                  "notes": null,
                  "imdb_id": "tt0088939"
               }
            ],
            "secondary": [
               {
                  "name": "Quincy Jones",
                  "notes": null,
                  "imdb_id": "nm0005065"
               },
               {
                  "name": "Jeremy Lubbock",
                  "notes": null,
                  "imdb_id": "nm0523835"
               },
               {
                  "name": "Rod Temperton",
                  "notes": null,
                  "imdb_id": "nm0854644"
               },
               {
                  "name": "Caiphus Semenya",
                  "notes": null,
                  "imdb_id": "nm0783783"
               },
               {
                  "name": "Andra\u00e9 Crouch",
                  "notes": null,
                  "imdb_id": "nm0189428"
               },
               {
                  "name": "Chris Boardman",
                  "notes": null,
                  "imdb_id": "nm0063973"
               },
               {
                  "name": "Jorge Calandrelli",
                  "notes": null,
                  "imdb_id": "nm0129326"
               },
               {
                  "name": "Joel Rosenbaum",
                  "notes": null,
                  "imdb_id": "nm0742139"
               },
               {
                  "name": "Fred Steiner",
                  "notes": null,
                  "imdb_id": "nm0006301"
               },
               {
                  "name": "Jack Hayes",
                  "notes": null,
                  "imdb_id": "nm0369948"
               },
               {
                  "name": "Jerry Hey",
                  "notes": null,
                  "imdb_id": "nm0382154"
               },
               {
                  "name": "Randy Kerber",
                  "notes": null,
                  "imdb_id": "nm0449205"
               }
            ]
         },
         {
            "notes": null,
            "won": false,
            "primary": [
               {
                  "name": "Witness",
                  "notes": null,
                  "imdb_id": "tt0090329"
               }
            ],
            "secondary": [
               {
                  "name": "Maurice Jarre",
                  "notes": null,
                  "imdb_id": "nm0003574"
               }
            ]
         }
      ]
   },
   {
      "category": "Best Music, Original Song",
      "nominations": [
         {
            "notes": "For the song \"Say You, Say Me\".",
            "won": true,
            "primary": [
               {
                  "name": "White Nights",
                  "notes": null,
                  "imdb_id": "tt0090319"
               }
            ],
            "secondary": [
               {
                  "name": "Lionel Richie",
                  "notes": null,
                  "imdb_id": "nm0005360"
               }
            ]
         },
         {
            "notes": "For the song \"Surprise, Surprise\".",
            "won": false,
            "primary": [
               {
                  "name": "A Chorus Line",
                  "notes": null,
                  "imdb_id": "tt0088915"
               }
            ],
            "secondary": [
               {
                  "name": "Marvin Hamlisch",
                  "notes": "(music)",
                  "imdb_id": "nm0006121"
               },
               {
                  "name": "Ed Kleban",
                  "notes": "(lyrics)",
                  "imdb_id": "nm0458505"
               }
            ]
         },
         {
            "notes": "For the song \"The Power of Love\".",
            "won": false,
            "primary": [
               {
                  "name": "Back to the Future",
                  "notes": null,
                  "imdb_id": "tt0088763"
               }
            ],
            "secondary": [
               {
                  "name": "Chris Hayes",
                  "notes": "(music)",
                  "imdb_id": "nm0370943"
               },
               {
                  "name": "Johnny Colla",
                  "notes": "(music)",
                  "imdb_id": "nm0171614"
               },
               {
                  "name": "Huey Lewis",
                  "notes": "(lyrics)",
                  "imdb_id": "nm0507271"
               }
            ]
         },
         {
            "notes": "For the song \"Miss Celie's Blues (Sister)\".",
            "won": false,
            "primary": [
               {
                  "name": "The Color Purple",
                  "notes": null,
                  "imdb_id": "tt0088939"
               }
            ],
            "secondary": [
               {
                  "name": "Quincy Jones",
                  "notes": "(music/lyrics)",
                  "imdb_id": "nm0005065"
               },
               {
                  "name": "Rod Temperton",
                  "notes": "(music/lyrics)",
                  "imdb_id": "nm0854644"
               },
               {
                  "name": "Lionel Richie",
                  "notes": "(lyrics)",
                  "imdb_id": "nm0005360"
               }
            ]
         },
         {
            "notes": "For the song \"Separate Lives (Love Theme from White Nights)\".",
            "won": false,
            "primary": [
               {
                  "name": "White Nights",
                  "notes": null,
                  "imdb_id": "tt0090319"
               }
            ],
            "secondary": [
               {
                  "name": "Stephen Bishop",
                  "notes": null,
                  "imdb_id": "nm0084196"
               }
            ]
         }
      ]
   },
   {
      "category": "Best Picture",
      "nominations": [
         {
            "notes": null,
            "won": true,
            "primary": [
               {
                  "name": "Out of Africa",
                  "notes": null,
                  "imdb_id": "tt0089755"
               }
            ],
            "secondary": [
               {
                  "name": "Sydney Pollack",
                  "notes": null,
                  "imdb_id": "nm0001628"
               }
            ]
         },
         {
            "notes": null,
            "won": false,
            "primary": [
               {
                  "name": "Kiss of the Spider Woman",
                  "notes": null,
                  "imdb_id": "tt0089424"
               }
            ],
            "secondary": [
               {
                  "name": "David Weisman",
                  "notes": null,
                  "imdb_id": "nm0918844"
               }
            ]
         },
         {
            "notes": null,
            "won": false,
            "primary": [
               {
                  "name": "Prizzi's Honor",
                  "notes": null,
                  "imdb_id": "tt0089841"
               }
            ],
            "secondary": [
               {
                  "name": "John Foreman",
                  "notes": null,
                  "imdb_id": "nm0286048"
               }
            ]
         },
         {
            "notes": null,
            "won": false,
            "primary": [
               {
                  "name": "The Color Purple",
                  "notes": null,
                  "imdb_id": "tt0088939"
               }
            ],
            "secondary": [
               {
                  "name": "Steven Spielberg",
                  "notes": null,
                  "imdb_id": "nm0000229"
               },
               {
                  "name": "Kathleen Kennedy",
                  "notes": null,
                  "imdb_id": "nm0005086"
               },
               {
                  "name": "Frank Marshall",
                  "notes": null,
                  "imdb_id": "nm0550881"
               },
               {
                  "name": "Quincy Jones",
                  "notes": null,
                  "imdb_id": "nm0005065"
               }
            ]
         },
         {
            "notes": null,
            "won": false,
            "primary": [
               {
                  "name": "Witness",
                  "notes": null,
                  "imdb_id": "tt0090329"
               }
            ],
            "secondary": [
               {
                  "name": "Edward S. Feldman",
                  "notes": null,
                  "imdb_id": "nm0271026"
               }
            ]
         }
      ]
   },
   {
      "category": "Best Short Film, Animated",
      "nominations": [
         {
            "notes": null,
            "won": true,
            "primary": [
               {
                  "name": "Anna & Bella",
                  "notes": null,
                  "imdb_id": "tt0088725"
               }
            ],
            "secondary": [
               {
                  "name": "Cilia van Dijk",
                  "notes": null,
                  "imdb_id": "nm0886580"
               }
            ]
         },
         {
            "notes": null,
            "won": false,
            "primary": [
               {
                  "name": "Second Class Mail",
                  "notes": null,
                  "imdb_id": "tt0089980"
               }
            ],
            "secondary": [
               {
                  "name": "Alison Snowden",
                  "notes": null,
                  "imdb_id": "nm0811345"
               }
            ]
         },
         {
            "notes": null,
            "won": false,
            "primary": [
               {
                  "name": "The Big Snit",
                  "notes": null,
                  "imdb_id": "tt0088805"
               }
            ],
            "secondary": [
               {
                  "name": "Richard Condie",
                  "notes": null,
                  "imdb_id": "nm0174345"
               },
               {
                  "name": "Michael J.F. Scott",
                  "notes": null,
                  "imdb_id": "nm0779569"
               }
            ]
         }
      ]
   },
   {
      "category": "Best Short Film, Live Action",
      "nominations": [
         {
            "notes": null,
            "won": true,
            "primary": [
               {
                  "name": "Molly's Pilgrim",
                  "notes": null,
                  "imdb_id": "tt0089612"
               }
            ],
            "secondary": [
               {
                  "name": "Jeffrey D. Brown",
                  "notes": null,
                  "imdb_id": "nm0113819"
               }
            ]
         },
         {
            "notes": null,
            "won": false,
            "primary": [
               {
                  "name": "Graffiti",
                  "notes": null,
                  "imdb_id": "tt0089225"
               }
            ],
            "secondary": [
               {
                  "name": "Dianna Costello",
                  "notes": null,
                  "imdb_id": "nm0182535"
               }
            ]
         },
         {
            "notes": null,
            "won": false,
            "primary": [
               {
                  "name": "Rainbow War",
                  "notes": null,
                  "imdb_id": "tt0089878"
               }
            ],
            "secondary": [
               {
                  "name": "Bob Rogers",
                  "notes": null,
                  "imdb_id": "nm0736748"
               }
            ]
         }
      ]
   },
   {
      "category": "Best Sound",
      "nominations": [
         {
            "notes": null,
            "won": true,
            "primary": [
               {
                  "name": "Out of Africa",
                  "notes": null,
                  "imdb_id": "tt0089755"
               }
            ],
            "secondary": [
               {
                  "name": "Chris Jenkins",
                  "notes": null,
                  "imdb_id": "nm0420804"
               },
               {
                  "name": "Gary Alexander",
                  "notes": null,
                  "imdb_id": "nm0018428"
               },
               {
                  "name": "Larry Stensvold",
                  "notes": null,
                  "imdb_id": "nm0826703"
               },
               {
                  "name": "Peter Handford",
                  "notes": null,
                  "imdb_id": "nm0359542"
               }
            ]
         },
         {
            "notes": null,
            "won": false,
            "primary": [
               {
                  "name": "A Chorus Line",
                  "notes": null,
                  "imdb_id": "tt0088915"
               }
            ],
            "secondary": [
               {
                  "name": "Donald O. Mitchell",
                  "notes": null,
                  "imdb_id": "nm0593290"
               },
               {
                  "name": "Michael Minkler",
                  "notes": null,
                  "imdb_id": "nm0591444"
               },
               {
                  "name": "Gerry Humphreys",
                  "notes": null,
                  "imdb_id": "nm0006836"
               },
               {
                  "name": "Christopher Newman",
                  "notes": null,
                  "imdb_id": "nm0628039"
               }
            ]
         },
         {
            "notes": null,
            "won": false,
            "primary": [
               {
                  "name": "Back to the Future",
                  "notes": null,
                  "imdb_id": "tt0088763"
               }
            ],
            "secondary": [
               {
                  "name": "Bill Varney",
                  "notes": null,
                  "imdb_id": "nm0890106"
               },
               {
                  "name": "B. Tennyson Sebastian II",
                  "notes": null,
                  "imdb_id": "nm0780928"
               },
               {
                  "name": "Robert Thirlwell",
                  "notes": null,
                  "imdb_id": "nm0858222"
               },
               {
                  "name": "William B. Kaplan",
                  "notes": null,
                  "imdb_id": "nm0438202"
               }
            ]
         },
         {
            "notes": null,
            "won": false,
            "primary": [
               {
                  "name": "Ladyhawke",
                  "notes": null,
                  "imdb_id": "tt0089457"
               }
            ],
            "secondary": [
               {
                  "name": "Les Fresholtz",
                  "notes": null,
                  "imdb_id": "nm0294370"
               },
               {
                  "name": "Rick Alexander",
                  "notes": "(as Dick Alexander)",
                  "imdb_id": "nm1219804"
               },
               {
                  "name": "Vern Poore",
                  "notes": null,
                  "imdb_id": "nm0691005"
               },
               {
                  "name": "Bud Alper",
                  "notes": null,
                  "imdb_id": "nm0022356"
               }
            ]
         },
         {
            "notes": null,
            "won": false,
            "primary": [
               {
                  "name": "Silverado",
                  "notes": null,
                  "imdb_id": "tt0090022"
               }
            ],
            "secondary": [
               {
                  "name": "Donald O. Mitchell",
                  "notes": null,
                  "imdb_id": "nm0593290"
               },
               {
                  "name": "Rick Kline",
                  "notes": null,
                  "imdb_id": "nm0459662"
               },
               {
                  "name": "Kevin O'Connell",
                  "notes": null,
                  "imdb_id": "nm0640114"
               },
               {
                  "name": "David M. Ronne",
                  "notes": null,
                  "imdb_id": "nm0740122"
               }
            ]
         }
      ]
   },
   {
      "category": "Best Writing, Screenplay Based on Material from Another Medium",
      "nominations": [
         {
            "notes": null,
            "won": true,
            "primary": [
               {
                  "name": "Out of Africa",
                  "notes": null,
                  "imdb_id": "tt0089755"
               }
            ],
            "secondary": [
               {
                  "name": "Kurt Luedtke",
                  "notes": null,
                  "imdb_id": "nm0525104"
               }
            ]
         },
         {
            "notes": null,
            "won": false,
            "primary": [
               {
                  "name": "Kiss of the Spider Woman",
                  "notes": null,
                  "imdb_id": "tt0089424"
               }
            ],
            "secondary": [
               {
                  "name": "Leonard Schrader",
                  "notes": null,
                  "imdb_id": "nm0775055"
               }
            ]
         },
         {
            "notes": null,
            "won": false,
            "primary": [
               {
                  "name": "Prizzi's Honor",
                  "notes": null,
                  "imdb_id": "tt0089841"
               }
            ],
            "secondary": [
               {
                  "name": "Richard Condon",
                  "notes": null,
                  "imdb_id": "nm0174410"
               },
               {
                  "name": "Janet Roach",
                  "notes": null,
                  "imdb_id": "nm0730027"
               }
            ]
         },
         {
            "notes": null,
            "won": false,
            "primary": [
               {
                  "name": "The Color Purple",
                  "notes": null,
                  "imdb_id": "tt0088939"
               }
            ],
            "secondary": [
               {
                  "name": "Menno Meyjes",
                  "notes": null,
                  "imdb_id": "nm0583675"
               }
            ]
         },
         {
            "notes": null,
            "won": false,
            "primary": [
               {
                  "name": "The Trip to Bountiful",
                  "notes": null,
                  "imdb_id": "tt0090203"
               }
            ],
            "secondary": [
               {
                  "name": "Horton Foote",
                  "notes": null,
                  "imdb_id": "nm0285210"
               }
            ]
         }
      ]
   },
   {
      "category": "Best Writing, Screenplay Written Directly for the Screen",
      "nominations": [
         {
            "notes": null,
            "won": true,
            "primary": [
               {
                  "name": "Witness",
                  "notes": null,
                  "imdb_id": "tt0090329"
               }
            ],
            "secondary": [
               {
                  "name": "Earl W. Wallace",
                  "notes": "(screenplay/story)",
                  "imdb_id": "nm0908620"
               },
               {
                  "name": "William Kelley",
                  "notes": "(screenplay/story)",
                  "imdb_id": "nm0446015"
               },
               {
                  "name": "Pamela Wallace",
                  "notes": "(story)",
                  "imdb_id": "nm0908807"
               }
            ]
         },
         {
            "notes": null,
            "won": false,
            "primary": [
               {
                  "name": "Back to the Future",
                  "notes": null,
                  "imdb_id": "tt0088763"
               }
            ],
            "secondary": [
               {
                  "name": "Robert Zemeckis",
                  "notes": null,
                  "imdb_id": "nm0000709"
               },
               {
                  "name": "Bob Gale",
                  "notes": null,
                  "imdb_id": "nm0301826"
               }
            ]
         },
         {
            "notes": null,
            "won": false,
            "primary": [
               {
                  "name": "Brazil",
                  "notes": null,
                  "imdb_id": "tt0088846"
               }
            ],
            "secondary": [
               {
                  "name": "Terry Gilliam",
                  "notes": null,
                  "imdb_id": "nm0000416"
               },
               {
                  "name": "Tom Stoppard",
                  "notes": null,
                  "imdb_id": "nm0001779"
               },
               {
                  "name": "Charles McKeown",
                  "notes": null,
                  "imdb_id": "nm0571650"
               }
            ]
         },
         {
            "notes": null,
            "won": false,
            "primary": [
               {
                  "name": "The Official Story",
                  "notes": null,
                  "imdb_id": "tt0089276"
               }
            ],
            "secondary": [
               {
                  "name": "Luis Puenzo",
                  "notes": null,
                  "imdb_id": "nm0699933"
               },
               {
                  "name": "A\u00edda Bortnik",
                  "notes": null,
                  "imdb_id": "nm0097548"
               }
            ]
         },
         {
            "notes": null,
            "won": false,
            "primary": [
               {
                  "name": "The Purple Rose of Cairo",
                  "notes": null,
                  "imdb_id": "tt0089853"
               }
            ],
            "secondary": [
               {
                  "name": "Woody Allen",
                  "notes": null,
                  "imdb_id": "nm0000095"
               }
            ]
         }
      ]
   }
]