[
   {
      "category": "Best Actor in a Leading Role",
      "nominations": [
         {
            "notes": null,
            "won": true,
            "primary": [
               {
                  "name": "Tom Hanks",
                  "notes": null,
                  "imdb_id": "nm0000158"
               }
            ],
            "secondary": [
               {
                  "name": "Philadelphia",
                  "notes": null,
                  "imdb_id": "tt0107818"
               }
            ]
         },
         {
            "notes": null,
            "won": false,
            "primary": [
               {
                  "name": "Anthony Hopkins",
                  "notes": null,
                  "imdb_id": "nm0000164"
               }
            ],
            "secondary": [
               {
                  "name": "The Remains of the Day",
                  "notes": null,
                  "imdb_id": "tt0107943"
               }
            ]
         },
         {
            "notes": null,
            "won": false,
            "primary": [
               {
                  "name": "Daniel Day-Lewis",
                  "notes": null,
                  "imdb_id": "nm0000358"
               }
            ],
            "secondary": [
               {
                  "name": "In the Name of the Father",
                  "notes": null,
                  "imdb_id": "tt0107207"
               }
            ]
         },
         {
            "notes": null,
            "won": false,
            "primary": [
               {
                  "name": "Laurence Fishburne",
                  "notes": null,
                  "imdb_id": "nm0000401"
               }
            ],
            "secondary": [
               {
                  "name": "What's Love Got to Do with It",
                  "notes": null,
                  "imdb_id": "tt0108551"
               }
            ]
         },
         {
            "notes": null,
            "won": false,
            "primary": [
               {
                  "name": "Liam Neeson",
                  "notes": null,
                  "imdb_id": "nm0000553"
               }
            ],
            "secondary": [
               {
                  "name": "Schindler's List",
                  "notes": null,
                  "imdb_id": "tt0108052"
               }
            ]
         }
      ]
   },
   {
      "category": "Best Actor in a Supporting Role",
      "nominations": [
         {
            "notes": null,
            "won": true,
            "primary": [
               {
                  "name": "Tommy Lee Jones",
                  "notes": null,
                  "imdb_id": "nm0000169"
               }
            ],
            "secondary": [
               {
                  "name": "The Fugitive",
                  "notes": null,
                  "imdb_id": "tt0106977"
               }
            ]
         },
         {
            "notes": null,
            "won": false,
            "primary": [
               {
                  "name": "John Malkovich",
                  "notes": null,
                  "imdb_id": "nm0000518"
               }
            ],
            "secondary": [
               {
                  "name": "In the Line of Fire",
                  "notes": null,
                  "imdb_id": "tt0107206"
               }
            ]
         },
         {
            "notes": null,
            "won": false,
            "primary": [
               {
                  "name": "Leonardo DiCaprio",
                  "notes": null,
                  "imdb_id": "nm0000138"
               }
            ],
            "secondary": [
               {
                  "name": "What's Eating Gilbert Grape",
                  "notes": null,
                  "imdb_id": "tt0108550"
               }
            ]
         },
         {
            "notes": null,
            "won": false,
            "primary": [
               {
                  "name": "Pete Postlethwaite",
                  "notes": null,
                  "imdb_id": "nm0000592"
               }
            ],
            "secondary": [
               {
                  "name": "In the Name of the Father",
                  "notes": null,
                  "imdb_id": "tt0107207"
               }
            ]
         },
         {
            "notes": null,
            "won": false,
            "primary": [
               {
                  "name": "Ralph Fiennes",
                  "notes": null,
                  "imdb_id": "nm0000146"
               }
            ],
            "secondary": [
               {
                  "name": "Schindler's List",
                  "notes": null,
                  "imdb_id": "tt0108052"
               }
            ]
         }
      ]
   },
   {
      "category": "Best Actress in a Leading Role",
      "nominations": [
         {
            "notes": null,
            "won": true,
            "primary": [
               {
                  "name": "Holly Hunter",
                  "notes": null,
                  "imdb_id": "nm0000456"
               }
            ],
            "secondary": [
               {
                  "name": "The Piano",
                  "notes": null,
                  "imdb_id": "tt0107822"
               }
            ]
         },
         {
            "notes": null,
            "won": false,
            "primary": [
               {
                  "name": "Angela Bassett",
                  "notes": null,
                  "imdb_id": "nm0000291"
               }
            ],
            "secondary": [
               {
                  "name": "What's Love Got to Do with It",
                  "notes": null,
                  "imdb_id": "tt0108551"
               }
            ]
         },
         {
            "notes": null,
            "won": false,
            "primary": [
               {
                  "name": "Debra Winger",
                  "notes": null,
                  "imdb_id": "nm0000700"
               }
            ],
            "secondary": [
               {
                  "name": "Shadowlands",
                  "notes": null,
                  "imdb_id": "tt0108101"
               }
            ]
         },
         {
            "notes": null,
            "won": false,
            "primary": [
               {
                  "name": "Emma Thompson",
                  "notes": null,
                  "imdb_id": "nm0000668"
               }
            ],
            "secondary": [
               {
                  "name": "The Remains of the Day",
                  "notes": null,
                  "imdb_id": "tt0107943"
               }
            ]
         },
         {
            "notes": null,
            "won": false,
            "primary": [
               {
                  "name": "Stockard Channing",
                  "notes": null,
                  "imdb_id": "nm0000330"
               }
            ],
            "secondary": [
               {
                  "name": "Six Degrees of Separation",
                  "notes": null,
                  "imdb_id": "tt0108149"
               }
            ]
         }
      ]
   },
   {
      "category": "Best Actress in a Supporting Role",
      "nominations": [
         {
            "notes": null,
            "won": true,
            "primary": [
               {
                  "name": "Anna Paquin",
                  "notes": null,
                  "imdb_id": "nm0001593"
               }
            ],
            "secondary": [
               {
                  "name": "The Piano",
                  "notes": null,
                  "imdb_id": "tt0107822"
               }
            ]
         },
         {
            "notes": null,
            "won": false,
            "primary": [
               {
                  "name": "Emma Thompson",
                  "notes": null,
                  "imdb_id": "nm0000668"
               }
            ],
            "secondary": [
               {
                  "name": "In the Name of the Father",
                  "notes": null,
                  "imdb_id": "tt0107207"
               }
            ]
         },
         {
            "notes": null,
            "won": false,
            "primary": [
               {
                  "name": "Holly Hunter",
                  "notes": null,
                  "imdb_id": "nm0000456"
               }
            ],
            "secondary": [
               {
                  "name": "The Firm",
                  "notes": null,
                  "imdb_id": "tt0106918"
               }
            ]
         },
         {
            "notes": null,
            "won": false,
            "primary": [
               {
                  "name": "Rosie Perez",
                  "notes": null,
                  "imdb_id": "nm0001609"
               }
            ],
            "secondary": [
               {
                  "name": "Fearless",
                  "notes": null,
                  "imdb_id": "tt0106881"
               }
            ]
         },
         {
            "notes": null,
            "won": false,
            "primary": [
               {
                  "name": "Winona Ryder",
                  "notes": null,
                  "imdb_id": "nm0000213"
               }
            ],
            "secondary": [
               {
                  "name": "The Age of Innocence",
                  "notes": null,
                  "imdb_id": "tt0106226"
               }
            ]
         }
      ]
   },
   {
      "category": "Best Art Direction-Set Decoration",
      "nominations": [
         {
            "notes": null,
            "won": true,
            "primary": [
               {
                  "name": "Schindler's List",
                  "notes": null,
                  "imdb_id": "tt0108052"
               }
            ],
            "secondary": [
               {
                  "name": "Allan Starski",
                  "notes": null,
                  "imdb_id": "nm0823649"
               },
               {
                  "name": "Ewa Braun",
                  "notes": null,
                  "imdb_id": "nm0105754"
               }
            ]
         },
         {
            "notes": null,
            "won": false,
            "primary": [
               {
                  "name": "Addams Family Values",
                  "notes": null,
                  "imdb_id": "tt0106220"
               }
            ],
            "secondary": [
               {
                  "name": "Ken Adam",
                  "notes": null,
                  "imdb_id": "nm0010553"
               },
               {
                  "name": "Marvin March",
                  "notes": null,
                  "imdb_id": "nm0545322"
               }
            ]
         },
         {
            "notes": null,
            "won": false,
            "primary": [
               {
                  "name": "Orlando",
                  "notes": null,
                  "imdb_id": "tt0107756"
               }
            ],
            "secondary": [
               {
                  "name": "Ben van Os",
                  "notes": null,
                  "imdb_id": "nm0651470"
               },
               {
                  "name": "Jan Roelfs",
                  "notes": null,
                  "imdb_id": "nm0736360"
               }
            ]
         },
         {
            "notes": null,
            "won": false,
            "primary": [
               {
                  "name": "The Age of Innocence",
                  "notes": null,
                  "imdb_id": "tt0106226"
               }
            ],
            "secondary": [
               {
                  "name": "Dante Ferretti",
                  "notes": null,
                  "imdb_id": "nm0274721"
               },
               {
                  "name": "Robert J. Franco",
                  "notes": null,
                  "imdb_id": "nm0290634"
               }
            ]
         },
         {
            "notes": null,
            "won": false,
            "primary": [
               {
                  "name": "The Remains of the Day",
                  "notes": null,
                  "imdb_id": "tt0107943"
               }
            ],
            "secondary": [
               {
                  "name": "Luciana Arrighi",
                  "notes": null,
                  "imdb_id": "nm0002186"
               },
               {
                  "name": "Ian Whittaker",
                  "notes": null,
                  "imdb_id": "nm0926434"
               }
            ]
         }
      ]
   },
   {
      "category": "Best Cinematography",
      "nominations": [
         {
            "notes": null,
            "won": true,
            "primary": [
               {
                  "name": "Schindler's List",
                  "notes": null,
                  "imdb_id": "tt0108052"
               }
            ],
            "secondary": [
               {
                  "name": "Janusz Kaminski",
                  "notes": null,
                  "imdb_id": "nm0001405"
               }
            ]
         },
         {
            "notes": null,
            "won": false,
            "primary": [
               {
                  "name": "Farewell My Concubine",
                  "notes": null,
                  "imdb_id": "tt0106332"
               }
            ],
            "secondary": [
               {
                  "name": "Changwei Gu",
                  "notes": null,
                  "imdb_id": "nm0345146"
               }
            ]
         },
         {
            "notes": null,
            "won": false,
            "primary": [
               {
                  "name": "Searching for Bobby Fischer",
                  "notes": null,
                  "imdb_id": "tt0108065"
               }
            ],
            "secondary": [
               {
                  "name": "Conrad L. Hall",
                  "notes": null,
                  "imdb_id": "nm0005734"
               }
            ]
         },
         {
            "notes": null,
            "won": false,
            "primary": [
               {
                  "name": "The Fugitive",
                  "notes": null,
                  "imdb_id": "tt0106977"
               }
            ],
            "secondary": [
               {
                  "name": "Michael Chapman",
                  "notes": null,
                  "imdb_id": "nm0152469"
               }
            ]
         },
         {
            "notes": null,
            "won": false,
            "primary": [
               {
                  "name": "The Piano",
                  "notes": null,
                  "imdb_id": "tt0107822"
               }
            ],
            "secondary": [
               {
                  "name": "Stuart Dryburgh",
                  "notes": null,
                  "imdb_id": "nm0238698"
               }
            ]
         }
      ]
   },
   {
      "category": "Best Costume Design",
      "nominations": [
         {
            "notes": null,
            "won": true,
            "primary": [
               {
                  "name": "The Age of Innocence",
                  "notes": null,
                  "imdb_id": "tt0106226"
               }
            ],
            "secondary": [
               {
                  "name": "Gabriella Pescucci",
                  "notes": null,
                  "imdb_id": "nm0675951"
               }
            ]
         },
         {
            "notes": null,
            "won": false,
            "primary": [
               {
                  "name": "Orlando",
                  "notes": null,
                  "imdb_id": "tt0107756"
               }
            ],
            "secondary": [
               {
                  "name": "Sandy Powell",
                  "notes": null,
                  "imdb_id": "nm0694309"
               }
            ]
         },
         {
            "notes": null,
            "won": false,
            "primary": [
               {
                  "name": "Schindler's List",
                  "notes": null,
                  "imdb_id": "tt0108052"
               }
            ],
            "secondary": [
               {
                  "name": "Anna B. Sheppard",
                  "notes": null,
                  "imdb_id": "nm0081318"
               }
            ]
         },
         {
            "notes": null,
            "won": false,
            "primary": [
               {
                  "name": "The Piano",
                  "notes": null,
                  "imdb_id": "tt0107822"
               }
            ],
            "secondary": [
               {
                  "name": "Janet Patterson",
                  "notes": null,
                  "imdb_id": "nm0666253"
               }
            ]
         },
         {
            "notes": null,
            "won": false,
            "primary": [
               {
                  "name": "The Remains of the Day",
                  "notes": null,
                  "imdb_id": "tt0107943"
               }
            ],
            "secondary": [
               {
                  "name": "Jenny Beavan",
                  "notes": null,
                  "imdb_id": "nm0064746"
               },
               {
                  "name": "John Bright",
                  "notes": null,
                  "imdb_id": "nm0109149"
               }
            ]
         }
      ]
   },
   {
      "category": "Best Director",
      "nominations": [
         {
            "notes": null,
            "won": true,
            "primary": [
               {
                  "name": "Steven Spielberg",
                  "notes": null,
                  "imdb_id": "nm0000229"
               }
            ],
            "secondary": [
               {
                  "name": "Schindler's List",
                  "notes": null,
                  "imdb_id": "tt0108052"
               }
            ]
         },
         {
            "notes": null,
            "won": false,
            "primary": [
               {
                  "name": "James Ivory",
                  "notes": null,
                  "imdb_id": "nm0412465"
               }
            ],
            "secondary": [
               {
                  "name": "The Remains of the Day",
                  "notes": null,
                  "imdb_id": "tt0107943"
               }
            ]
         },
         {
            "notes": null,
            "won": false,
            "primary": [
               {
                  "name": "Jane Campion",
                  "notes": null,
                  "imdb_id": "nm0001005"
               }
            ],
            "secondary": [
               {
                  "name": "The Piano",
                  "notes": null,
                  "imdb_id": "tt0107822"
               }
            ]
         },
         {
            "notes": null,
            "won": false,
            "primary": [
               {
                  "name": "Jim Sheridan",
                  "notes": null,
                  "imdb_id": "nm0006487"
               }
            ],
            "secondary": [
               {
                  "name": "In the Name of the Father",
                  "notes": null,
                  "imdb_id": "tt0107207"
               }
            ]
         },
         {
            "notes": null,
            "won": false,
            "primary": [
               {
                  "name": "Robert Altman",
                  "notes": null,
                  "imdb_id": "nm0000265"
               }
            ],
            "secondary": [
               {
                  "name": "Short Cuts",
                  "notes": null,
                  "imdb_id": "tt0108122"
               }
            ]
         }
      ]
   },
   {
      "category": "Best Documentary, Features",
      "nominations": [
         {
            "notes": null,
            "won": true,
            "primary": [
               {
                  "name": "I Am a Promise: The Children of Stanton Elementary School",
                  "notes": null,
                  "imdb_id": "tt0107177"
               }
            ],
            "secondary": [
               {
                  "name": "Susan Raymond",
                  "notes": null,
                  "imdb_id": "nm0713371"
               },
               {
                  "name": "Alan Raymond",
                  "notes": null,
                  "imdb_id": "nm0713203"
               }
            ]
         },
         {
            "notes": null,
            "won": false,
            "primary": [
               {
                  "name": "Children of Fate: Life and Death in a Sicilian Family",
                  "notes": null,
                  "imdb_id": "tt0106556"
               }
            ],
            "secondary": [
               {
                  "name": "Susan Todd",
                  "notes": null,
                  "imdb_id": "nm0865295"
               },
               {
                  "name": "Andrew Young",
                  "notes": null,
                  "imdb_id": "nm0949255"
               }
            ]
         },
         {
            "notes": null,
            "won": false,
            "primary": [
               {
                  "name": "For Better or for Worse",
                  "notes": null,
                  "imdb_id": "tt0106939"
               }
            ],
            "secondary": [
               {
                  "name": "David Collier",
                  "notes": null,
                  "imdb_id": "nm0171891"
               },
               {
                  "name": "Betsy Thompson",
                  "notes": null,
                  "imdb_id": "nm0859889"
               }
            ]
         },
         {
            "notes": null,
            "won": false,
            "primary": [
               {
                  "name": "The Broadcast Tapes of Dr. Peter",
                  "notes": null,
                  "imdb_id": "tt0106485"
               }
            ],
            "secondary": [
               {
                  "name": "David Paperny",
                  "notes": null,
                  "imdb_id": "nm0660431"
               },
               {
                  "name": "Arthur Ginsberg",
                  "notes": null,
                  "imdb_id": "nm0320092"
               }
            ]
         },
         {
            "notes": null,
            "won": false,
            "primary": [
               {
                  "name": "The War Room",
                  "notes": null,
                  "imdb_id": "tt0108515"
               }
            ],
            "secondary": [
               {
                  "name": "D.A. Pennebaker",
                  "notes": null,
                  "imdb_id": "nm0672060"
               },
               {
                  "name": "Chris Hegedus",
                  "notes": null,
                  "imdb_id": "nm0373698"
               }
            ]
         }
      ]
   },
   {
      "category": "Best Documentary, Short Subjects",
      "nominations": [
         {
            "notes": null,
            "won": true,
            "primary": [
               {
                  "name": "Defending Our Lives",
                  "notes": null,
                  "imdb_id": "tt0106694"
               }
            ],
            "secondary": [
               {
                  "name": "Margaret Lazarus",
                  "notes": null,
                  "imdb_id": "nm0493822"
               },
               {
                  "name": "Renner Wunderlich",
                  "notes": null,
                  "imdb_id": "nm0943337"
               }
            ]
         },
         {
            "notes": null,
            "won": false,
            "primary": [
               {
                  "name": "Blood Ties: The Life and Work of Sally Mann",
                  "notes": null,
                  "imdb_id": "tt0106431"
               }
            ],
            "secondary": [
               {
                  "name": "Steven Cantor",
                  "notes": null,
                  "imdb_id": "nm0134682"
               },
               {
                  "name": "Peter Spirer",
                  "notes": null,
                  "imdb_id": "nm0819033"
               }
            ]
         },
         {
            "notes": null,
            "won": false,
            "primary": [
               {
                  "name": "Chicks in White Satin",
                  "notes": null,
                  "imdb_id": "tt0106555"
               }
            ],
            "secondary": [
               {
                  "name": "Elaine Holliman",
                  "notes": null,
                  "imdb_id": "nm0391097"
               },
               {
                  "name": "Jason Schneider",
                  "notes": null,
                  "imdb_id": "nm0773873"
               }
            ]
         }
      ]
   },
   {
      "category": "Best Effects, Sound Effects Editing",
      "nominations": [
         {
            "notes": null,
            "won": true,
            "primary": [
               {
                  "name": "Jurassic Park",
                  "notes": null,
                  "imdb_id": "tt0107290"
               }
            ],
            "secondary": [
               {
                  "name": "Gary Rydstrom",
                  "notes": null,
                  "imdb_id": "nm0003977"
               },
               {
                  "name": "Richard Hymns",
                  "notes": null,
                  "imdb_id": "nm0405232"
               }
            ]
         },
         {
            "notes": null,
            "won": false,
            "primary": [
               {
                  "name": "Cliffhanger",
                  "notes": null,
                  "imdb_id": "tt0106582"
               }
            ],
            "secondary": [
               {
                  "name": "Wylie Stateman",
                  "notes": null,
                  "imdb_id": "nm0823758"
               },
               {
                  "name": "Gregg Baxter",
                  "notes": null,
                  "imdb_id": "nm0062741"
               }
            ]
         },
         {
            "notes": null,
            "won": false,
            "primary": [
               {
                  "name": "The Fugitive",
                  "notes": null,
                  "imdb_id": "tt0106977"
               }
            ],
            "secondary": [
               {
                  "name": "John Leveque",
                  "notes": null,
                  "imdb_id": "nm0505311"
               },
               {
                  "name": "Bruce Stambler",
                  "notes": null,
                  "imdb_id": "nm0821801"
               }
            ]
         }
      ]
   },
   {
      "category": "Best Effects, Visual Effects",
      "nominations": [
         {
            "notes": null,
            "won": true,
            "primary": [
               {
                  "name": "Jurassic Park",
                  "notes": null,
                  "imdb_id": "tt0107290"
               }
            ],
            "secondary": [
               {
                  "name": "Dennis Muren",
                  "notes": null,
                  "imdb_id": "nm0613830"
               },
               {
                  "name": "Stan Winston",
                  "notes": null,
                  "imdb_id": "nm0935644"
               },
               {
                  "name": "Phil Tippett",
                  "notes": null,
                  "imdb_id": "nm0864138"
               },
               {
                  "name": "Michael Lantieri",
                  "notes": null,
                  "imdb_id": "nm0487177"
               }
            ]
         },
         {
            "notes": null,
            "won": false,
            "primary": [
               {
                  "name": "Cliffhanger",
                  "notes": null,
                  "imdb_id": "tt0106582"
               }
            ],
            "secondary": [
               {
                  "name": "Neil Krepela",
                  "notes": null,
                  "imdb_id": "nm0470878"
               },
               {
                  "name": "John Richardson",
                  "notes": null,
                  "imdb_id": "nm0724624"
               },
               {
                  "name": "John Bruno",
                  "notes": null,
                  "imdb_id": "nm0116497"
               },
               {
                  "name": "Pamela Easley",
                  "notes": null,
                  "imdb_id": "nm0247476"
               }
            ]
         },
         {
            "notes": null,
            "won": false,
            "primary": [
               {
                  "name": "The Nightmare Before Christmas",
                  "notes": null,
                  "imdb_id": "tt0107688"
               }
            ],
            "secondary": [
               {
                  "name": "Pete Kozachik",
                  "notes": null,
                  "imdb_id": "nm0468757"
               },
               {
                  "name": "Eric Leighton",
                  "notes": null,
                  "imdb_id": "nm0500343"
               },
               {
                  "name": "Ariel Velasco-Shaw",
                  "notes": null,
                  "imdb_id": "nm0892333"
               },
               {
                  "name": "Gordon Baker",
                  "notes": null,
                  "imdb_id": "nm0048490"
               }
            ]
         }
      ]
   },
   {
      "category": "Best Film Editing",
      "nominations": [
         {
            "notes": null,
            "won": true,
            "primary": [
               {
                  "name": "Schindler's List",
                  "notes": null,
                  "imdb_id": "tt0108052"
               }
            ],
            "secondary": [
               {
                  "name": "Michael Kahn",
                  "notes": null,
                  "imdb_id": "nm0434883"
               }
            ]
         },
         {
            "notes": null,
            "won": false,
            "primary": [
               {
                  "name": "In the Line of Fire",
                  "notes": null,
                  "imdb_id": "tt0107206"
               }
            ],
            "secondary": [
               {
                  "name": "Anne V. Coates",
                  "notes": null,
                  "imdb_id": "nm0167613"
               }
            ]
         },
         {
            "notes": null,
            "won": false,
            "primary": [
               {
                  "name": "In the Name of the Father",
                  "notes": null,
                  "imdb_id": "tt0107207"
               }
            ],
            "secondary": [
               {
                  "name": "Gerry Hambling",
                  "notes": null,
                  "imdb_id": "nm0357421"
               }
            ]
         },
         {
            "notes": null,
            "won": false,
            "primary": [
               {
                  "name": "The Fugitive",
                  "notes": null,
                  "imdb_id": "tt0106977"
               }
            ],
            "secondary": [
               {
                  "name": "Dennis Virkler",
                  "notes": null,
                  "imdb_id": "nm0899398"
               },
               {
                  "name": "David Finfer",
                  "notes": null,
                  "imdb_id": "nm0277722"
               },
               {
                  "name": "Dean Goodhill",
                  "notes": null,
                  "imdb_id": "nm0328923"
               },
               {
                  "name": "Don Brochu",
                  "notes": null,
                  "imdb_id": "nm0110519"
               },
               {
                  "name": "Richard Nord",
                  "notes": null,
                  "imdb_id": "nm0621301"
               },
               {
                  "name": "Dov Hoenig",
                  "notes": null,
                  "imdb_id": "nm0388516"
               }
            ]
         },
         {
            "notes": null,
            "won": false,
            "primary": [
               {
                  "name": "The Piano",
                  "notes": null,
                  "imdb_id": "tt0107822"
               }
            ],
            "secondary": [
               {
                  "name": "Veronika Jenet",
                  "notes": null,
                  "imdb_id": "nm0353074"
               }
            ]
         }
      ]
   },
   {
      "category": "Best Foreign Language Film",
      "nominations": [
         {
            "notes": "Spain.",
            "won": true,
            "primary": [
               {
                  "name": "Belle Epoque",
                  "notes": null,
                  "imdb_id": "tt0103791"
               }
            ],
            "secondary": []
         },
         {
            "notes": "Hong Kong.",
            "won": false,
            "primary": [
               {
                  "name": "Farewell My Concubine",
                  "notes": null,
                  "imdb_id": "tt0106332"
               }
            ],
            "secondary": []
         },
         {
            "notes": "United Kingdom.",
            "won": false,
            "primary": [
               {
                  "name": "Hedd Wyn",
                  "notes": null,
                  "imdb_id": "tt0104403"
               }
            ],
            "secondary": []
         },
         {
            "notes": "Vietnam.",
            "won": false,
            "primary": [
               {
                  "name": "The Scent of Green Papaya",
                  "notes": null,
                  "imdb_id": "tt0107617"
               }
            ],
            "secondary": []
         },
         {
            "notes": "Taiwan.",
            "won": false,
            "primary": [
               {
                  "name": "The Wedding Banquet",
                  "notes": null,
                  "imdb_id": "tt0107156"
               }
            ],
            "secondary": []
         }
      ]
   },
   {
      "category": "Best Makeup",
      "nominations": [
         {
            "notes": null,
            "won": true,
            "primary": [
               {
                  "name": "Mrs. Doubtfire",
                  "notes": null,
                  "imdb_id": "tt0107614"
               }
            ],
            "secondary": [
               {
                  "name": "Greg Cannom",
                  "notes": null,
                  "imdb_id": "nm0134148"
               },
               {
                  "name": "Ve Neill",
                  "notes": null,
                  "imdb_id": "nm0624763"
               },
               {
                  "name": "Yolanda Toussieng",
                  "notes": null,
                  "imdb_id": "nm0869758"
               }
            ]
         },
         {
            "notes": null,
            "won": false,
            "primary": [
               {
                  "name": "Philadelphia",
                  "notes": null,
                  "imdb_id": "tt0107818"
               }
            ],
            "secondary": [
               {
                  "name": "Carl Fullerton",
                  "notes": null,
                  "imdb_id": "nm0298379"
               },
               {
                  "name": "Alan D'Angerio",
                  "notes": null,
                  "imdb_id": "nm0195310"
               }
            ]
         },
         {
            "notes": null,
            "won": false,
            "primary": [
               {
                  "name": "Schindler's List",
                  "notes": null,
                  "imdb_id": "tt0108052"
               }
            ],
            "secondary": [
               {
                  "name": "Christina Smith",
                  "notes": null,
                  "imdb_id": "nm0807702"
               },
               {
                  "name": "Matthew W. Mungle",
                  "notes": null,
                  "imdb_id": "nm0612817"
               },
               {
                  "name": "Judith A. Cory",
                  "notes": null,
                  "imdb_id": "nm0181677"
               }
            ]
         }
      ]
   },
   {
      "category": "Best Music, Original Score",
      "nominations": [
         {
            "notes": null,
            "won": true,
            "primary": [
               {
                  "name": "Schindler's List",
                  "notes": null,
                  "imdb_id": "tt0108052"
               }
            ],
            "secondary": [
               {
                  "name": "John Williams",
                  "notes": null,
                  "imdb_id": "nm0002354"
               }
            ]
         },
         {
            "notes": null,
            "won": false,
            "primary": [
               {
                  "name": "The Age of Innocence",
                  "notes": null,
                  "imdb_id": "tt0106226"
               }
            ],
            "secondary": [
               {
                  "name": "Elmer Bernstein",
                  "notes": null,
                  "imdb_id": "nm0000930"
               }
            ]
         },
         {
            "notes": null,
            "won": false,
            "primary": [
               {
                  "name": "The Firm",
                  "notes": null,
                  "imdb_id": "tt0106918"
               }
            ],
            "secondary": [
               {
                  "name": "Dave Grusin",
                  "notes": null,
                  "imdb_id": "nm0006115"
               }
            ]
         },
         {
            "notes": null,
            "won": false,
            "primary": [
               {
                  "name": "The Fugitive",
                  "notes": null,
                  "imdb_id": "tt0106977"
               }
            ],
            "secondary": [
               {
                  "name": "James Newton Howard",
                  "notes": null,
                  "imdb_id": "nm0006133"
               }
            ]
         },
         {
            "notes": null,
            "won": false,
            "primary": [
               {
                  "name": "The Remains of the Day",
                  "notes": null,
                  "imdb_id": "tt0107943"
               }
            ],
            "secondary": [
               {
                  "name": "Richard Robbins",
                  "notes": null,
                  "imdb_id": "nm0006442"
               }
            ]
         }
      ]
   },
   {
      "category": "Best Music, Original Song",
      "nominations": [
         {
            "notes": "For the song \"Streets of Philadelphia\".",
            "won": true,
            "primary": [
               {
                  "name": "Philadelphia",
                  "notes": null,
                  "imdb_id": "tt0107818"
               }
            ],
            "secondary": [
               {
                  "name": "Bruce Springsteen",
                  "notes": null,
                  "imdb_id": "nm0819803"
               }
            ]
         },
         {
            "notes": "For the song \"The Day I Fall in Love\".",
            "won": false,
            "primary": [
               {
                  "name": "Beethoven's 2nd",
                  "notes": null,
                  "imdb_id": "tt0106375"
               }
            ],
            "secondary": [
               {
                  "name": "Carole Bayer Sager",
                  "notes": null,
                  "imdb_id": "nm0004728"
               },
               {
                  "name": "James Ingram",
                  "notes": null,
                  "imdb_id": "nm0408986"
               },
               {
                  "name": "Clif Magness",
                  "notes": null,
                  "imdb_id": "nm0536221"
               }
            ]
         },
         {
            "notes": "For the song \"Philadelphia\".",
            "won": false,
            "primary": [
               {
                  "name": "Philadelphia",
                  "notes": null,
                  "imdb_id": "tt0107818"
               }
            ],
            "secondary": [
               {
                  "name": "Neil Young",
                  "notes": null,
                  "imdb_id": "nm0949918"
               }
            ]
         },
         {
            "notes": "For the song \"Again\".",
            "won": false,
            "primary": [
               {
                  "name": "Poetic Justice",
                  "notes": null,
                  "imdb_id": "tt0107840"
               }
            ],
            "secondary": [
               {
                  "name": "Janet Jackson",
                  "notes": null,
                  "imdb_id": "nm0001390"
               },
               {
                  "name": "Jimmy Jam",
                  "notes": null,
                  "imdb_id": "nm0005047"
               },
               {
                  "name": "Terry Lewis",
                  "notes": null,
                  "imdb_id": "nm0507805"
               }
            ]
         },
         {
            "notes": "For the song \"A Wink and a Smile\".",
            "won": false,
            "primary": [
               {
                  "name": "Sleepless in Seattle",
                  "notes": null,
                  "imdb_id": "tt0108160"
               }
            ],
            "secondary": [
               {
                  "name": "Marc Shaiman",
                  "notes": "(music)",
                  "imdb_id": "nm0003299"
               },
               {
                  "name": "Ramsay McLean",
                  "notes": "(lyrics)",
                  "imdb_id": "nm0572634"
               }
            ]
         }
      ]
   },
   {
      "category": "Best Picture",
      "nominations": [
         {
            "notes": null,
            "won": true,
            "primary": [
               {
                  "name": "Schindler's List",
                  "notes": null,
                  "imdb_id": "tt0108052"
               }
            ],
            "secondary": [
               {
                  "name": "Steven Spielberg",
                  "notes": null,
                  "imdb_id": "nm0000229"
               },
               {
                  "name": "Gerald R. Molen",
                  "notes": null,
                  "imdb_id": "nm0596520"
               },
               {
                  "name": "Branko Lustig",
                  "notes": null,
                  "imdb_id": "nm0527322"
               }
            ]
         },
         {
            "notes": null,
            "won": false,
            "primary": [
               {
                  "name": "In the Name of the Father",
                  "notes": null,
                  "imdb_id": "tt0107207"
               }
            ],
            "secondary": [
               {
                  "name": "Jim Sheridan",
                  "notes": null,
                  "imdb_id": "nm0006487"
               }
            ]
         },
         {
            "notes": null,
            "won": false,
            "primary": [
               {
                  "name": "The Fugitive",
                  "notes": null,
                  "imdb_id": "tt0106977"
               }
            ],
            "secondary": [
               {
                  "name": "Arnold Kopelson",
                  "notes": null,
                  "imdb_id": "nm0465745"
               }
            ]
         },
         {
            "notes": null,
            "won": false,
            "primary": [
               {
                  "name": "The Piano",
                  "notes": null,
                  "imdb_id": "tt0107822"
               }
            ],
            "secondary": [
               {
                  "name": "Jan Chapman",
                  "notes": null,
                  "imdb_id": "nm0152396"
               }
            ]
         },
         {
            "notes": null,
            "won": false,
            "primary": [
               {
                  "name": "The Remains of the Day",
                  "notes": null,
                  "imdb_id": "tt0107943"
               }
            ],
            "secondary": [
               {
                  "name": "Mike Nichols",
                  "notes": null,
                  "imdb_id": "nm0001566"
               },
               {
                  "name": "John Calley",
                  "notes": null,
                  "imdb_id": "nm0130492"
               },
               {
                  "name": "Ismail Merchant",
                  "notes": null,
                  "imdb_id": "nm0580337"
               }
            ]
         }
      ]
   },
   {
      "category": "Best Short Film, Animated",
      "nominations": [
         {
            "notes": null,
            "won": true,
            "primary": [
               {
                  "name": "The Wrong Trousers",
                  "notes": null,
                  "imdb_id": "tt0108598"
               }
            ],
            "secondary": [
               {
                  "name": "Nick Park",
                  "notes": null,
                  "imdb_id": "nm0661910"
               }
            ]
         },
         {
            "notes": null,
            "won": false,
            "primary": [
               {
                  "name": "Blindscape",
                  "notes": null,
                  "imdb_id": "tt0106428"
               }
            ],
            "secondary": [
               {
                  "name": "Stephen Palmer",
                  "notes": null,
                  "imdb_id": "nm0658453"
               }
            ]
         },
         {
            "notes": null,
            "won": false,
            "primary": [
               {
                  "name": "Small Talk",
                  "notes": null,
                  "imdb_id": "tt0108165"
               }
            ],
            "secondary": [
               {
                  "name": "Bob Godfrey",
                  "notes": null,
                  "imdb_id": "nm0323962"
               },
               {
                  "name": "Kevin Baldwin",
                  "notes": null,
                  "imdb_id": "nm0049950"
               }
            ]
         },
         {
            "notes": null,
            "won": false,
            "primary": [
               {
                  "name": "The Mighty River",
                  "notes": null,
                  "imdb_id": "tt0107574"
               }
            ],
            "secondary": [
               {
                  "name": "Fr\u00e9d\u00e9ric Back",
                  "notes": null,
                  "imdb_id": "nm0045610"
               },
               {
                  "name": "Hubert Tison",
                  "notes": null,
                  "imdb_id": "nm0864361"
               }
            ]
         },
         {
            "notes": null,
            "won": false,
            "primary": [
               {
                  "name": "The Village",
                  "notes": null,
                  "imdb_id": "tt0108494"
               }
            ],
            "secondary": [
               {
                  "name": "Mark Baker",
                  "notes": null,
                  "imdb_id": "nm0048735"
               }
            ]
         }
      ]
   },
   {
      "category": "Best Short Film, Live Action",
      "nominations": [
         {
            "notes": null,
            "won": true,
            "primary": [
               {
                  "name": "Black Rider",
                  "notes": null,
                  "imdb_id": "tt0108056"
               }
            ],
            "secondary": [
               {
                  "name": "Pepe Danquart",
                  "notes": null,
                  "imdb_id": "nm0200500"
               }
            ]
         },
         {
            "notes": null,
            "won": false,
            "primary": [
               {
                  "name": "Down on the Waterfront",
                  "notes": null,
                  "imdb_id": "tt0106766"
               }
            ],
            "secondary": [
               {
                  "name": "Stacy Title",
                  "notes": null,
                  "imdb_id": "nm0864468"
               },
               {
                  "name": "Jonathan Penner",
                  "notes": null,
                  "imdb_id": "nm0672103"
               }
            ]
         },
         {
            "notes": null,
            "won": false,
            "primary": [
               {
                  "name": "Partners",
                  "notes": null,
                  "imdb_id": "tt0110781"
               }
            ],
            "secondary": [
               {
                  "name": "Peter Weller",
                  "notes": null,
                  "imdb_id": "nm0000693"
               },
               {
                  "name": "Jana Sue Memel",
                  "notes": null,
                  "imdb_id": "nm0578604"
               }
            ]
         },
         {
            "notes": null,
            "won": false,
            "primary": [
               {
                  "name": "The Dutch Master",
                  "notes": null,
                  "imdb_id": "tt0112917"
               }
            ],
            "secondary": [
               {
                  "name": "Susan Seidelman",
                  "notes": null,
                  "imdb_id": "nm0782384"
               },
               {
                  "name": "Jonathan Brett",
                  "notes": null,
                  "imdb_id": "nm0107954"
               }
            ]
         },
         {
            "notes": null,
            "won": false,
            "primary": [
               {
                  "name": "The Screw",
                  "notes": null,
                  "imdb_id": "tt0108498"
               }
            ],
            "secondary": [
               {
                  "name": "Didier Flamand",
                  "notes": null,
                  "imdb_id": "nm0280955"
               }
            ]
         }
      ]
   },
   {
      "category": "Best Sound",
      "nominations": [
         {
            "notes": null,
            "won": true,
            "primary": [
               {
                  "name": "Jurassic Park",
                  "notes": null,
                  "imdb_id": "tt0107290"
               }
            ],
            "secondary": [
               {
                  "name": "Gary Summers",
                  "notes": null,
                  "imdb_id": "nm0838707"
               },
               {
                  "name": "Gary Rydstrom",
                  "notes": null,
                  "imdb_id": "nm0003977"
               },
               {
                  "name": "Shawn Murphy",
                  "notes": null,
                  "imdb_id": "nm0004156"
               },
               {
                  "name": "Ron Judkins",
                  "notes": null,
                  "imdb_id": "nm0431954"
               }
            ]
         },
         {
            "notes": null,
            "won": false,
            "primary": [
               {
                  "name": "Cliffhanger",
                  "notes": null,
                  "imdb_id": "tt0106582"
               }
            ],
            "secondary": [
               {
                  "name": "Michael Minkler",
                  "notes": null,
                  "imdb_id": "nm0591444"
               },
               {
                  "name": "Bob Beemer",
                  "notes": null,
                  "imdb_id": "nm0066446"
               },
               {
                  "name": "Tim Cooney",
                  "notes": null,
                  "imdb_id": "nm0177784"
               }
            ]
         },
         {
            "notes": null,
            "won": false,
            "primary": [
               {
                  "name": "Geronimo: An American Legend",
                  "notes": null,
                  "imdb_id": "tt0107004"
               }
            ],
            "secondary": [
               {
                  "name": "Chris Carpenter",
                  "notes": null,
                  "imdb_id": "nm0139303"
               },
               {
                  "name": "Doug Hemphill",
                  "notes": null,
                  "imdb_id": "nm0376153"
               },
               {
                  "name": "Bill W. Benton",
                  "notes": null,
                  "imdb_id": "nm0072904"
               },
               {
                  "name": "Lee Orloff",
                  "notes": null,
                  "imdb_id": "nm0650090"
               }
            ]
         },
         {
            "notes": null,
            "won": false,
            "primary": [
               {
                  "name": "Schindler's List",
                  "notes": null,
                  "imdb_id": "tt0108052"
               }
            ],
            "secondary": [
               {
                  "name": "Andy Nelson",
                  "notes": null,
                  "imdb_id": "nm0625144"
               },
               {
                  "name": "Steve Pederson",
                  "notes": null,
                  "imdb_id": "nm0670007"
               },
               {
                  "name": "Scott Millan",
                  "notes": null,
                  "imdb_id": "nm0586793"
               },
               {
                  "name": "Ron Judkins",
                  "notes": null,
                  "imdb_id": "nm0431954"
               }
            ]
         },
         {
            "notes": null,
            "won": false,
            "primary": [
               {
                  "name": "The Fugitive",
                  "notes": null,
                  "imdb_id": "tt0106977"
               }
            ],
            "secondary": [
               {
                  "name": "Donald O. Mitchell",
                  "notes": null,
                  "imdb_id": "nm0593290"
               },
               {
                  "name": "Michael Herbick",
                  "notes": null,
                  "imdb_id": "nm0378655"
               },
               {
                  "name": "Frank A. Monta\u00f1o",
                  "notes": null,
                  "imdb_id": "nm0599057"
               },
               {
                  "name": "Scott D. Smith",
                  "notes": null,
                  "imdb_id": "nm0809896"
               }
            ]
         }
      ]
   },
   {
      "category": "Best Writing, Screenplay Based on Material Previously Produced or Published",
      "nominations": [
         {
            "notes": null,
            "won": true,
            "primary": [
               {
                  "name": "Schindler's List",
                  "notes": null,
                  "imdb_id": "tt0108052"
               }
            ],
            "secondary": [
               {
                  "name": "Steven Zaillian",
                  "notes": null,
                  "imdb_id": "nm0001873"
               }
            ]
         },
         {
            "notes": null,
            "won": false,
            "primary": [
               {
                  "name": "In the Name of the Father",
                  "notes": null,
                  "imdb_id": "tt0107207"
               }
            ],
            "secondary": [
               {
                  "name": "Terry George",
                  "notes": null,
                  "imdb_id": "nm0313623"
               },
               {
                  "name": "Jim Sheridan",
                  "notes": null,
                  "imdb_id": "nm0006487"
               }
            ]
         },
         {
            "notes": null,
            "won": false,
            "primary": [
               {
                  "name": "Shadowlands",
                  "notes": null,
                  "imdb_id": "tt0108101"
               }
            ],
            "secondary": [
               {
                  "name": "William Nicholson",
                  "notes": null,
                  "imdb_id": "nm0629933"
               }
            ]
         },
         {
            "notes": null,
            "won": false,
            "primary": [
               {
                  "name": "The Age of Innocence",
                  "notes": null,
                  "imdb_id": "tt0106226"
               }
            ],
            "secondary": [
               {
                  "name": "Jay Cocks",
                  "notes": null,
                  "imdb_id": "nm0168379"
               },
               {
                  "name": "Martin Scorsese",
                  "notes": null,
                  "imdb_id": "nm0000217"
               }
            ]
         },
         {
            "notes": null,
            "won": false,
            "primary": [
               {
                  "name": "The Remains of the Day",
                  "notes": null,
                  "imdb_id": "tt0107943"
               }
            ],
            "secondary": [
               {
                  "name": "Ruth Prawer Jhabvala",
                  "notes": null,
                  "imdb_id": "nm0695609"
               }
            ]
         }
      ]
   },
   {
      "category": "Best Writing, Screenplay Written Directly for the Screen",
      "nominations": [
         {
            "notes": null,
            "won": true,
            "primary": [
               {
                  "name": "The Piano",
                  "notes": null,
                  "imdb_id": "tt0107822"
               }
            ],
            "secondary": [
               {
                  "name": "Jane Campion",
                  "notes": null,
                  "imdb_id": "nm0001005"
               }
            ]
         },
         {
            "notes": null,
            "won": false,
            "primary": [
               {
                  "name": "Dave",
                  "notes": null,
                  "imdb_id": "tt0106673"
               }
            ],
            "secondary": [
               {
                  "name": "Gary Ross",
                  "notes": null,
                  "imdb_id": "nm0002657"
               }
            ]
         },
         {
            "notes": null,
            "won": false,
            "primary": [
               {
                  "name": "In the Line of Fire",
                  "notes": null,
                  "imdb_id": "tt0107206"
               }
            ],
            "secondary": [
               {
                  "name": "Jeff Maguire",
                  "notes": null,
                  "imdb_id": "nm0536587"
               }
            ]
         },
         {
            "notes": null,
            "won": false,
            "primary": [
               {
                  "name": "Philadelphia",
                  "notes": null,
                  "imdb_id": "tt0107818"
               }
            ],
            "secondary": [
               {
                  "name": "Ron Nyswaner",
                  "notes": null,
                  "imdb_id": "nm0638913"
               }
            ]
         },
         {
            "notes": null,
            "won": false,
            "primary": [
               {
                  "name": "Sleepless in Seattle",
                  "notes": null,
                  "imdb_id": "tt0108160"
               }
            ],
            "secondary": [
               {
                  "name": "Nora Ephron",
                  "notes": "(screenplay)",
                  "imdb_id": "nm0001188"
               },
               {
                  "name": "David S. Ward",
                  "notes": "(screenplay)",
                  "imdb_id": "nm0911486"
               },
               {
                  "name": "Jeff Arch",
                  "notes": "(screenplay/story)",
                  "imdb_id": "nm0033578"
               }
            ]
         }
      ]
   }
]